.gitattributes
.pylintrc
.travis.yml
AUTHORS
ChangeLog
LICENSE
MANIFEST.in
Makefile
README.md
requirements.txt
setup.cfg
setup.py
backslash/__init__.py
backslash/__version__.py
backslash/_compat.py
backslash/api.py
backslash/api_object.py
backslash/archiveable.py
backslash/client.py
backslash/comment.py
backslash/commentable.py
backslash/compatibility.py
backslash/error.py
backslash/error_container.py
backslash/exceptions.py
backslash/field_filters.py
backslash/lazy_query.py
backslash/metadata_holder.py
backslash/related_entity_container.py
backslash/session.py
backslash/suite.py
backslash/test.py
backslash/timing_container.py
backslash/user.py
backslash/utils.py
backslash/warning.py
backslash/warning_container.py
backslash.egg-info/PKG-INFO
backslash.egg-info/SOURCES.txt
backslash.egg-info/dependency_links.txt
backslash.egg-info/not-zip-safe
backslash.egg-info/pbr.json
backslash.egg-info/requires.txt
backslash.egg-info/top_level.txt
backslash/contrib/__init__.py
backslash/contrib/keepalive_thread.py
backslash/contrib/slash_plugin.py
backslash/contrib/utils.py
docs/changelog.rst
docs/conf.py
docs/index.rst
docs/requirements.txt
docs/_static/backslash-logo.png
tests/__init__.py
tests/conftest.py
tests/test_api_object.py
tests/test_backslash.py
tests/test_environment_metadata.py
tests/test_lazy_query.py
tests/test_normalize_file_path.py
tests/test_readme_doctest.py
tests/test_slash_plugin.py
tests/test_urls.py
tests/test_utils.py