Metadata-Version: 2.1
Name: backslash
Version: 2.38.0
Summary: Client library for the Backslash test reporting service
Home-page: http://github.com/getslash/backslash-python/
Author: Rotem Yaari
Author-email: vmalloc@gmail.com
License: BSD
Platform: UNKNOWN
Classifier: Programming Language :: Python :: 2.7
Classifier: Programming Language :: Python :: 3.5
Classifier: Programming Language :: Python :: 3.6
Provides-Extra: testing
Provides-Extra: sentry
